test_mypip_setup/__init__.py
test_mypip_setup/test2.py
test_mypip_setup-0.2.2.dist-info/METADATA
test_mypip_setup-0.2.2.dist-info/WHEEL
test_mypip_setup-0.2.2.dist-info/entry_points.txt
test_mypip_setup-0.2.2.dist-info/top_level.txt
test_mypip_setup-0.2.2.dist-info/RECORD
