Metadata-Version: 2.4
Name: test_mypip_setup
Version: 0.2.2
Summary: 一个跨平台的Python示例包
Author-email: Your Name <your.email@example.com>
License: MIT
Project-URL: Homepage, https://github.com/yourusername/test1v2
Project-URL: Bug Tracker, https://github.com/yourusername/test1v2/issues
Classifier: Development Status :: 3 - Alpha
Classifier: Intended Audience :: Developers
Classifier: License :: OSI Approved :: MIT License
Classifier: Operating System :: OS Independent
Classifier: Programming Language :: Python :: 3.10
Classifier: Programming Language :: Python :: 3.11
Requires-Python: >=3.10
